[
  {
    "name": "Kristoffer Strube",
    "class": 2017,
    "title": "Formand",
    "image": "strube.jpg",
    "email": "strube@dsau.dk"
  },
  {
    "name": "Søren Eriksen",
    "class": 2017,
    "title": "Næstformand",
    "image": "søren.jpg",
    "email": "eriksen@dsau.dk"
  },
  {
    "name": "Mathias Tversted",
    "image": "tversted.jpg",
    "title": "Kasserer",
    "email": "tversted@dsau.dk",
    "class": 2017
  },
  {
    "name": "Erik Funder Carstensen",
    "class": 2017,
    "title": "Sponsoransvarlig",
    "image": "erik.jpg",
    "email": "erik@dsau.dk"
  },
  {
    "name": "Casper Rysgaard",
    "class": 2017,
    "title": "Menig",
    "image": "rysgaard.png",
    "email": "rysgaard@dsau.dk"
  },
  {
    "name": "Christian Zhuang-Qing Nielsen",
    "class": 2015,
    "title": "Menig",
    "image": "christian.jpg",
    "email": "czn@dsau.dk"
  },
  {
    "name": "Thomas Øther Rasmussen",
    "image": "oether.jpg",
    "title": "Menig",
    "email": "oether@dsau.dk",
    "class": 2016
  },
  {
    "name": "Jeppe Kristensen",
    "image": "jeppe.jpg",
    "title": "Menig",
    "email": "jeppe@dsau.dk",
    "class": 2017
  },
  {
    "name": "Magdalena Kalin",
    "image": "magdalena.jpg",
    "title": "Menig",
    "email": "magdalena@dsau.dk",
    "class": 2018
  },
  {
    "name": "Simon Dohn",
    "image": "dohn.jpg",
    "title": "Menig",
    "email": "dohn@dsau.dk",
    "class": 2019
  },
  {
    "name": "Ulrik Boll Djurtoft ",
    "image": "ulrik.jpg",
    "title": "Revisor",
    "email": "ulrik@dsau.dk",
    "class": 2014
  }
]
